blog_vi/__init__.py
blog_vi/__main__.py
blog_vi/_cli.py
blog_vi/_config.py
blog_vi/_settings.py
blog_vi/utils.py
blog_vi/core/__init__.py
blog_vi/core/article.py
blog_vi/core/landing.py
blog_vi/core/tracker.py
blog_vi/core/utils.py
blog_vi/core/translations/__init__.py
blog_vi/core/translations/engine.py
blog_vi/core/translations/exceptions.py
blog_vi/core/translations/registry.py
blog_vi/core/translations/providers/__init__.py
blog_vi/core/translations/providers/base.py
blog_vi/core/translations/providers/deepl.py
blog_vi/core/translations/providers/google.py
blog_vi/templates/article.html
blog_vi/templates/blog.html
blog_vi/templates/card.html
blog_vi/templates/favicon.html
blog_vi/templates/footer.html
blog_vi/templates/header.html
blog_vi/templates/lead_card.html
blog_vi/templates/subscription_form.html
blog_vi/templates/assets/css/tailwind.min.css
blog_vi/templates/assets/css/typography.min.css
blog_vi/templates/assets/js/reading-time.min.js
blog_vi/templates/assets/js/search.js
blog_vi/templates/assets/js/sharect.js
blog_vi-0.2.6.dist-info/LICENSE
blog_vi-0.2.6.dist-info/METADATA
blog_vi-0.2.6.dist-info/WHEEL
blog_vi-0.2.6.dist-info/entry_points.txt
blog_vi-0.2.6.dist-info/top_level.txt
blog_vi-0.2.6.dist-info/RECORD
