Metadata-Version: 2.1
Name: blog-vi
Version: 0.2.6
Summary: Simple blog with search and comments
Home-page: https://github.com/LikaloLLC/BlogVi
Author: Likalo Limited
Author-email: hello@docsie.io
Keywords: blog-vi(勝利)
Classifier: Development Status :: 3 - Alpha
Classifier: Intended Audience :: Developers
Classifier: License :: OSI Approved :: Apache Software License
Classifier: Programming Language :: Python :: 3
Classifier: Programming Language :: Python :: 3.5
Classifier: Programming Language :: Python :: 3.6
Classifier: Programming Language :: Python :: 3.7
Classifier: Programming Language :: Python :: 3.8
Classifier: Programming Language :: Python :: 3.9
Requires-Python: >=3.5, <4
License-File: LICENSE
Requires-Dist: Markdown <3.2.2,>=3.0.0
Requires-Dist: click <8.0,>=7.0
Requires-Dist: watchdog <2.0.0,>=1.0.0
Requires-Dist: requests <2.22.0,>=2.0.0
Requires-Dist: Jinja2 <2.22.0,>=2.0.0
Requires-Dist: jinja-markdown <=1.200630,>=1.200000
Requires-Dist: feedgen <1.0.0,>=0.6.0
Requires-Dist: python-slugify <4.0.1,>=4.0.0
Requires-Dist: PyYAML <5.3.1,>=5.0.0
Requires-Dist: deepl <2,>=1.0.1
Requires-Dist: MarkupSafe ==2.0.1
